LICENSE
MANIFEST.in
README.rst
setup.py
admin_highcharts/__init__.py
admin_highcharts/admin.py
admin_highcharts/models.py
admin_highcharts/tests.py
admin_highcharts/views.py
admin_highcharts/locale/en/LC_MESSAGES/django.mo
admin_highcharts/locale/en/LC_MESSAGES/django.po
admin_highcharts/locale/zh_CN/LC_MESSAGES/django.mo
admin_highcharts/locale/zh_CN/LC_MESSAGES/django.po
admin_highcharts/static/admin_highcharts/js/exporting.js
admin_highcharts/static/admin_highcharts/js/highcharts.js
admin_highcharts/static/admin_highcharts/js/jquery-2.0.2.js
admin_highcharts/templates/admin_highcharts/change_list.html
admin_highcharts/templates/admin_highcharts/js.html
admin_highcharts/templatetags/__init__.py
admin_highcharts/templatetags/highcharts_tag.py
django_admin_highcharts.egg-info/PKG-INFO
django_admin_highcharts.egg-info/SOURCES.txt
django_admin_highcharts.egg-info/dependency_links.txt
django_admin_highcharts.egg-info/not-zip-safe
django_admin_highcharts.egg-info/top_level.txt