Metadata-Version: 1.1
Name: django-admin-highcharts
Version: 0.1.1
Summary: Django app to add highcharts into django admin
Home-page: https://github.com/nieoding/django-admin-highcharts
Author: nieo ding
Author-email: dingzh@66wifi.com
License: BSD License
Platform: UNKNOWN
Classifier: Environment :: Web Environment
Classifier: Framework :: Django
Classifier: Intended Audience :: Developers
Classifier: License :: OSI Approved :: BSD License
Classifier: Operating System :: OS Independent
Classifier: Programming Language :: Python
Classifier: Programming Language :: Python :: 2.7
Classifier: Topic :: Internet :: WWW/HTTP
Classifier: Topic :: Internet :: WWW/HTTP :: Dynamic Content
